{"reports": [{"param": "mScaleDragDetector", "annotation": "javax.annotation.Nullable", "jump": 1, "compulsory": "false", "location": "CLASS_FIELD", "class": "com.github.chrisbanes.photoview.PhotoViewAttacher", "followups": [], "index": "0", "pkg": "com.github.chrisbanes.photoview", "uri": "///tmp/projects/PhotoView/photoview/src/main/java/com/github/chrisbanes/photoview/PhotoViewAttacher.java", "method": "null", "inject": "true"}, {"param": "attr", "annotation": "javax.annotation.Nullable", "jump": 0, "compulsory": "false", "location": "METHOD_PARAM", "class": "com.github.chrisbanes.photoview.PhotoView", "followups": [], "index": "1", "pkg": "com.github.chrisbanes.photoview", "uri": "///tmp/projects/PhotoView/photoview/src/main/java/com/github/chrisbanes/photoview/PhotoView.java", "method": "PhotoView(android.content.Context,android.util.AttributeSet)", "inject": "true"}, {"param": "null", "annotation": "javax.annotation.Nullable", "jump": 0, "compulsory": "false", "location": "METHOD_RETURN", "class": "com.github.chrisbanes.photoview.PhotoViewAttacher", "followups": [], "index": "0", "pkg": "com.github.chrisbanes.photoview", "uri": "///tmp/projects/PhotoView/photoview/src/main/java/com/github/chrisbanes/photoview/PhotoViewAttacher.java", "method": "getDisplayRect(android.graphics.Matrix)", "inject": "true"}, {"param": "mCurrentFlingRunnable", "annotation": "javax.annotation.Nullable", "jump": -1, "compulsory": "false", "location": "CLASS_FIELD", "class": "com.github.chrisbanes.photoview.PhotoViewAttacher", "followups": [], "index": "0", "pkg": "com.github.chrisbanes.photoview", "uri": "///tmp/projects/PhotoView/photoview/src/main/java/com/github/chrisbanes/photoview/PhotoViewAttacher.java", "method": "null", "inject": "true"}, {"param": "pendingScaleType", "annotation": "javax.annotation.Nullable", "jump": -2, "compulsory": "false", "location": "CLASS_FIELD", "class": "com.github.chrisbanes.photoview.PhotoView", "followups": [], "index": "0", "pkg": "com.github.chrisbanes.photoview", "uri": "///tmp/projects/PhotoView/photoview/src/main/java/com/github/chrisbanes/photoview/PhotoView.java", "method": "null", "inject": "true"}, {"param": "mVelocityTracker", "annotation": "javax.annotation.Nullable", "jump": -3, "compulsory": "false", "location": "CLASS_FIELD", "class": "com.github.chrisbanes.photoview.CustomGestureDetector", "followups": [], "index": "0", "pkg": "com.github.chrisbanes.photoview", "uri": "///tmp/projects/PhotoView/photoview/src/main/java/com/github/chrisbanes/photoview/CustomGestureDetector.java", "method": "null", "inject": "true"}, {"param": "null", "annotation": "javax.annotation.Nullable", "jump": 0, "compulsory": "false", "location": "METHOD_RETURN", "class": "com.github.chrisbanes.photoview.PhotoViewAttacher", "followups": [], "index": "0", "pkg": "com.github.chrisbanes.photoview", "uri": "///tmp/projects/PhotoView/photoview/src/main/java/com/github/chrisbanes/photoview/PhotoViewAttacher.java", "method": "getDisplayRect()", "inject": "true"}, {"param": "attr", "annotation": "javax.annotation.Nullable", "jump": -1, "compulsory": "false", "location": "METHOD_PARAM", "class": "com.github.chrisbanes.photoview.PhotoView", "followups": [], "index": "1", "pkg": "com.github.chrisbanes.photoview", "uri": "///tmp/projects/PhotoView/photoview/src/main/java/com/github/chrisbanes/photoview/PhotoView.java", "method": "PhotoView(android.content.Context,android.util.AttributeSet,int)", "inject": "true"}, {"param": "null", "annotation": "javax.annotation.Nullable", "jump": -1, "compulsory": "false", "location": "METHOD_RETURN", "class": "com.github.chrisbanes.photoview.PhotoView", "followups": [], "index": "0", "pkg": "com.github.chrisbanes.photoview", "uri": "///tmp/projects/PhotoView/photoview/src/main/java/com/github/chrisbanes/photoview/PhotoView.java", "method": "getDisplayRect()", "inject": "true"}]}